simpleth/__init__.py
simpleth/simpleth.py
simpleth-0.1.65.data/data/artifacts/HelloWorld1.abi
simpleth-0.1.65.data/data/artifacts/HelloWorld1.bin
simpleth-0.1.65.data/data/artifacts/HelloWorld2.abi
simpleth-0.1.65.data/data/artifacts/HelloWorld2.bin
simpleth-0.1.65.data/data/artifacts/HelloWorld3.abi
simpleth-0.1.65.data/data/artifacts/HelloWorld3.bin
simpleth-0.1.65.data/data/artifacts/HelloWorld4.abi
simpleth-0.1.65.data/data/artifacts/HelloWorld4.bin
simpleth-0.1.65.data/data/artifacts/Test.abi
simpleth-0.1.65.data/data/artifacts/Test.bin
simpleth-0.1.65.data/data/contracts/HelloWorld1.sol
simpleth-0.1.65.data/data/contracts/HelloWorld2.sol
simpleth-0.1.65.data/data/contracts/HelloWorld3.sol
simpleth-0.1.65.data/data/contracts/HelloWorld4.sol
simpleth-0.1.65.data/data/contracts/Test.sol
simpleth-0.1.65.data/data/examples/event_poll.py
simpleth-0.1.65.data/data/examples/hello_world1.py
simpleth-0.1.65.data/data/examples/hello_world2.py
simpleth-0.1.65.data/data/examples/hello_world3.py
simpleth-0.1.65.data/data/examples/hello_world4.py
simpleth-0.1.65.dist-info/LICENSE.txt
simpleth-0.1.65.dist-info/METADATA
simpleth-0.1.65.dist-info/WHEEL
simpleth-0.1.65.dist-info/top_level.txt
simpleth-0.1.65.dist-info/RECORD
