Metadata-Version: 2.1
Name: simpleth
Version: 0.1.65
Summary: Simplified Ethereum for Python
Home-page: https://github.com/snewell4/simpleth
Author: Stephen Newell
Author-email: <snewell4@gmail.com>
License: MIT
Keywords: blockchain,ganache,Solidity,ethereum,smart-contract,contract
Classifier: Development Status :: 3 - Alpha
Classifier: License :: OSI Approved :: MIT License
Classifier: Programming Language :: Python :: 3
Classifier: Operating System :: Microsoft :: Windows
Classifier: Topic :: Other/Nonlisted Topic
Requires-Python: >=3.8
License-File: LICENSE.txt
Requires-Dist: web3 (>=5.23.0)
Requires-Dist: attributedict (>=0.3.0)
Requires-Dist: hexbytes (>=0.2.2)
